gnmi/__init__.py
gnmi-0.0.0a0.dist-info/WHEEL
gnmi-0.0.0a0.dist-info/METADATA
gnmi-0.0.0a0.dist-info/RECORD
