Metadata-Version: 2.1
Name: gnmi
Version: 0.0.0a0
Summary: A Python gNxI project namespace package
Home-page: https://github.com/python-gnxi
Author: Arun Babu Neelicattu
Author-email: arun.neelicattu@gmail.com
Requires-Python: >=3.6,<4.0
Classifier: Development Status :: 1 - Planning
Classifier: Programming Language :: Python :: 3
Classifier: Programming Language :: Python :: 3.6
Classifier: Programming Language :: Python :: 3.7
Classifier: Programming Language :: Python :: 3.8
Project-URL: Repository, https://github.com/python-gnxi
